pycytools/__init__.py
pycytools/library.py
pycytools/plots.py
pycytools/transformations.py
pycytools/external/__init__.py
pycytools/external/optimal_leaf_ordering.py
pycytools-0.6.9.dist-info/LICENSE
pycytools-0.6.9.dist-info/METADATA
pycytools-0.6.9.dist-info/WHEEL
pycytools-0.6.9.dist-info/top_level.txt
pycytools-0.6.9.dist-info/RECORD
