Metadata-Version: 2.1
Name: pycytools
Version: 0.6.9
Summary: Helper functions to handle image cytometry data.
Home-page: https://github.com/BodenmillerGroup/pycytools
Author: Vito Zanotelli, Matthias Leutenegger, Bodenmiller Lab UZH
Author-email: vito.zanotelli@gmail.com
License: BSD-3 License
Platform: UNKNOWN
Requires-Dist: numpy
Requires-Dist: scipy
Requires-Dist: pandas
Requires-Dist: requests
Requires-Dist: scikit-image
Requires-Dist: tifffile
